owletpy/OwletPy.py
owletpy/__init__.py
owletpy-1.0.14.dist-info/LICENSE
owletpy-1.0.14.dist-info/METADATA
owletpy-1.0.14.dist-info/WHEEL
owletpy-1.0.14.dist-info/top_level.txt
owletpy-1.0.14.dist-info/RECORD
