Metadata-Version: 2.1
Name: owletpy
Version: 1.0.14
Summary: Python client for Owlet monitors
Home-page: https://github.com/CAB426/owletpy
Author: CAB426, mbevand, craigjmidwinter, angel12
Author-email: CAB426@gmail.com
License: UNKNOWN
Keywords: owlet baby
Platform: UNKNOWN
Requires-Dist: requests (>=2.23.0)
